{"stat.chestOpened":43,"stat.walkOneCm":782870,"stat.playerKills":5,"stat.leaveGame":5,"stat.useItem.minecraft.tnt":2,"stat.useItem.minecraft.potion":1,"stat.useItem.minecraft.end_stone":26,"stat.jump":1370,"stat.swimOneCm":14157,"stat.fallOneCm":62253,"stat.climbOneCm":1152,"stat.useItem.minecraft.planks":14,"stat.crouchOneCm":39033,"stat.mineBlock.minecraft.wool":43,"stat.useItem.minecraft.obsidian":7,"stat.sprintOneCm":365267,"achievement.exploreAllBiomes":{"value":0,"progress":["Mega Taiga Hills","Mega Taiga"]},"stat.useItem.minecraft.water_bucket":1,"achievement.openInventory":16,"stat.damageTaken":6227,"stat.useItem.minecraft.wooden_pickaxe":1,"stat.useItem.minecraft.golden_apple":1,"stat.flyOneCm":412017,"stat.deaths":30,"stat.mineBlock.minecraft.planks":3,"stat.playOneMinute":125049,"stat.useItem.minecraft.wooden_sword":28,"stat.mineBlock.minecraft.glass":1,"stat.useItem.minecraft.stone_sword":14,"stat.mineBlock.minecraft.end_stone":1,"stat.useItem.minecraft.shears":20,"stat.damageDealt":3264,"stat.useItem.minecraft.wool":412,"stat.timeSinceDeath":791,"stat.useItem.minecraft.wooden_axe":4,"stat.diveOneCm":12143}